bioplumber/.DS_Store
bioplumber/__init__.py
bioplumber/abundance.py
bioplumber/alignment.py
bioplumber/assemble.py
bioplumber/bining.py
bioplumber/configs.json
bioplumber/configs.py
bioplumber/dereplication.py
bioplumber/file_studio.py
bioplumber/files.py
bioplumber/qc.py
bioplumber/slurm.py
bioplumber/slurm_template.txt
bioplumber/taxonomy.py
bioplumber/tui.py
bioplumber/tui_css.tcss
bioplumber-1.3.3.dist-info/METADATA
bioplumber-1.3.3.dist-info/WHEEL
bioplumber-1.3.3.dist-info/entry_points.txt
bioplumber-1.3.3.dist-info/RECORD
