Metadata-Version: 2.3
Name: bioplumber
Version: 1.3.3
Summary: 
Author: ParsaGhadermazi
Author-email: 54489047+ParsaGhadermazi@users.noreply.github.com
Requires-Python: >=3.10,<4.0
Classifier: Programming Language :: Python :: 3
Classifier: Programming Language :: Python :: 3.10
Classifier: Programming Language :: Python :: 3.11
Classifier: Programming Language :: Python :: 3.12
Classifier: Programming Language :: Python :: 3.13
Requires-Dist: ipywidgets (>=8.1.5,<9.0.0)
Requires-Dist: pandas (>=2.2.3,<3.0.0)
Requires-Dist: requests (>=2.32.3,<3.0.0)
Requires-Dist: rich (>=13.8.1,<14.0.0)
Requires-Dist: textual[syntax] (==1.0.0)
